Workbook

Sheet Executive Dashboard
B1: HIDDEN MARGIN RECOVERY ANALYSIS | J1: Annual Revenue: | K1: 100000000
B2: Pacific Northwest Carton Converting | FY 2024 | J2: Implementation Cost: | K2: 263000
B4: Total Identified Recovery | D4: EBITDA Improvement | F4: Payback Period | H4: ROI | J4: KEY ASSUMPTIONS
B5: =C16 -> 2234061.1 | D5: =B5/K1 -> 0.022340611 | F5: =K2/B5*12 -> 1.412674 | H5: =B5/K2 -> 8.4945291 | J5: PPV Capture Rate: | K5: =ANALYSIS_PPV!B15 -> 0.022
B6: Annual $ | D6: Points | F6: Months | H6: x | J6: HIGH Scrap Reduction: | K6: =ANALYSIS_Scrap!B34 -> 0.12
J7: Energy Gap Closure: | K7: =ANALYSIS_Energy!B21 -> 0.75
J8: Phantom Margin Recovery: | K8: =ANALYSIS_Contribution!B35 -> 0.093
B9: RECOVERY BY INITIATIVE
B11: Initiative | C11: Annual Impact | D11: % of Total | E11: Timeline | F11: Complexity
B12: Standard Cost Refresh | C12: =ANALYSIS_PPV!B18 -> 848854.37 | D12: =IF($C$16=0,0,C12/$C$16) -> 0.37996022 | E12: 30 days | F12: Low
B13: Scrap Reduction Program | C13: =ANALYSIS_Scrap!B40 -> 614290.41 | D13: =IF($C$16=0,0,C13/$C$16) -> 0.2749658 | E13: 6 months | F13: Medium
B14: Energy Optimization | C14: =ANALYSIS_Energy!B26 -> 354392.11 | D14: =IF($C$16=0,0,C14/$C$16) -> 0.15863134 | E14: 45 days | F14: Low
B15: SKU Rationalization | C15: =ANALYSIS_Contribution!B38 -> 416524.26 | D15: =IF($C$16=0,0,C15/$C$16) -> 0.18644264 | E15: 90 days | F15: Medium
B16: TOTAL | C16: =SUM(C12:C15) -> 2234061.1

Sheet Assumptions
A1: MODEL ASSUMPTIONS
A3: All assumptions below (highlighted yellow) can be adjusted to run scenarios.
A4: Blue text = hardcoded inputs; Black text = formulas
A6: Category | B6: Assumption | C6: Value | D6: Link | E6: Notes
A7: PPV | B7: Std Cost Update Capture Rate | C7: =ANALYSIS_PPV!B15 -> 0.022 | D7: ANALYSIS_PPV!B15 | E7: % of unfavorable PPV recoverable via std cost refresh
A8: Scrap | B8: HIGH Complexity Reduction Target | C8: =ANALYSIS_Scrap!B34 -> 0.12 | D8: ANALYSIS_Scrap!B34 | E8: % reduction achievable for HIGH complexity SKUs
A9: Scrap | B9: MEDIUM Complexity Reduction Target | C9: =ANALYSIS_Scrap!B35 -> 0.05 | D9: ANALYSIS_Scrap!B35 | E9: % reduction achievable for MEDIUM complexity SKUs
A10: Scrap | B10: TCOQ Multiplier | C10: =ANALYSIS_Scrap!N1 -> 2.4 | D10: ANALYSIS_Scrap!N1 | E10: True cost of quality multiplier (industry std: 2-3x)
A11: Energy | B11: Achievable Gap Closure | C11: =ANALYSIS_Energy!B21 -> 0.75 | D11: ANALYSIS_Energy!B21 | E11: % of efficiency gap that can be closed
A12: Energy | B12: Project Multiplier | C12: =ANALYSIS_Energy!B25 -> 18.7 | D12: ANALYSIS_Energy!B25 | E12: Scaling factor for scenario targets
A13: SKU | B13: Phantom Margin Recovery Rate | C13: =ANALYSIS_Contribution!B35 -> 0.093 | D13: ANALYSIS_Contribution!B35 | E13: % of phantom margin gap recoverable via rationalization

Sheet RAW_Production_Orders
A1: Order_Number | B1: Plant | C1: SKU | D1: Order_Date | E1: Completion_Date | F1: Planned_Qty_000s | G1: Good_Qty_000s | H1: Scrap_Qty_000s | I1: Scrap_Rate | J1: Production_Line | K1: Std_Material_Cost | L1: Std_Labor_Cost | M1: Std_VOH_Cost | N1: Std_FOH_Cost | O1: Std_Total_Cost | P1: Actual_Material_Cost | Q1: Actual_Labor_Cost | R1: Actual_VOH_Cost | S1: Actual_FOH_Cost | T1: Actual_Total_Cost | U1: Material_Variance | V1: Labor_Variance | W1: VOH_Variance | X1: FOH_Variance | Y1: Total_Variance | Z1: Month
A2: PO-1000001 | B2: 1000 | C2: SKU-2004 | D2: 2024-01-13 | E2: 2024-01-16 | F2: 400 | G2: 385 | H2: 15 | I2: 0.0365 | J2: 2 | K2: 14404 | L2: 2471.84 | M2: 1624 | N2: 2535.68 | O2: 21035.52 | P2: 15129.39 | Q2: 2794.62 | R2: 1651.27 | S2: 2535.68 | T2: 22110.96 | U2: 725.39 | V2: 322.78 | W2: 27.27 | X2: 0 | Y2: 1075.44 | Z2: 2024-01
A3: PO-1000002 | B3: 1000 | C3: SKU-1004 | D3: 2024-01-16 | E3: 2024-01-17 | F3: 373 | G3: 362 | H3: 11 | I3: 0.0275 | J3: 2 | K3: 11613.36 | L3: 2304.99 | M3: 1514.38 | N3: 2364.52 | O3: 17797.25 | P3: 12033.65 | Q3: 2533.35 | R3: 1627.79 | S3: 2364.52 | T3: 18559.31 | U3: 420.29 | V3: 228.35 | W3: 113.41 | X3: 0 | Y3: 762.06 | Z3: 2024-01
A4: PO-1000003 | B4: 1000 | C4: SKU-1004 | D4: 2024-08-17 | E4: 2024-08-20 | F4: 156 | G4: 150 | H4: 6 | I4: 0.0354 | J4: 2 | K4: 4857.06 | L4: 964.02 | M4: 633.36 | N4: 988.92 | O4: 7443.35 | P4: 4899.37 | Q4: 993.76 | R4: 643.24 | S4: 988.92 | T4: 7525.28 | U4: 42.31 | V4: 29.74 | W4: 9.88 | X4: 0 | Y4: 81.93 | Z4: 2024-08
A5: PO-1000004 | B5: 1000 | C5: SKU-4455 | D5: 2024-02-22 | E5: 2024-02-23 | F5: 539 | G5: 498 | H5: 41 | I5: 0.0747 | J5: 2 | K5: 20040.02 | L5: 3330.8 | M5: 2188.34 | N5: 3416.83 | O5: 28975.99 | P5: 21605.55 | Q5: 4241.04 | R5: 2676.38 | S5: 3416.83 | T5: 31939.8 | U5: 1565.53 | V5: 910.23 | W5: 488.04 | X5: 0 | Y5: 2963.81 | Z5: 2024-02
A6: PO-1000005 | B6: 1000 | C6: SKU-5455 | D6: 2024-07-12 | E6: 2024-07-13 | F6: 715 | G6: 673 | H6: 42 | I6: 0.0587 | J6: 2 | K6: 32625.45 | L6: 4418.41 | M6: 2902.9 | N6: 4532.53 | O6: 44479.29 | P6: 34388.97 | Q6: 5307.98 | R6: 3422.82 | S6: 4532.53 | T6: 47652.3 | U6: 1763.52 | V6: 889.57 | W6: 519.92 | X6: 0 | Y6: 3173 | Z6: 2024-07
A7: PO-1000006 | B7: 1000 | C7: SKU-2005 | D7: 2024-05-28 | E7: 2024-05-29 | F7: 388 | G7: 370 | H7: 18 | I7: 0.0444 | J7: 1 | K7: 13417.04 | L7: 2397.68 | M7: 1575.28 | N7: 2459.61 | O7: 19849.61 | P7: 13805.52 | Q7: 2419.13 | R7: 1627.91 | S7: 2459.61 | T7: 20312.17 | U7: 388.48 | V7: 21.44 | W7: 52.63 | X7: 0 | Y7: 462.55 | Z7: 2024-05
A8: PO-1000007 | B8: 1000 | C8: SKU-1002 | D8: 2024-06-30 | E8: 2024-07-02 | F8: 423 | G8: 409 | H8: 14 | I8: 0.0322 | J8: 1 | K8: 12867.66 | L8: 2613.97 | M8: 1717.38 | N8: 2681.48 | O8: 19880.49 | P8: 13439.11 | Q8: 2507.54 | R8: 1740.56 | S8: 2681.48 | T8: 20368.69 | U8: 571.45 | V8: -106.43 | W8: 23.18 | X8: 0 | Y8: 488.2 | Z8: 2024-06
A9: PO-1000008 | B9: 1000 | C9: SKU-2001 | D9: 2024-05-05 | E9: 2024-05-07 | F9: 623 | G9: 601 | H9: 22 | I9: 0.0346 | J9: 1 | K9: 21178.88 | L9: 3849.89 | M9: 2529.38 | N9: 3949.32 | O9: 31507.48 | P9: 22607.19 | Q9: 3977.71 | R9: 2543.78 | S9: 3949.32 | T9: 33078.01 | U9: 1428.31 | V9: 127.82 | W9: 14.4 | X9: 0 | Y9: 1570.53 | Z9: 2024-05
A10: PO-1000009 | B10: 1000 | C10: SKU-2005 | D10: 2024-01-29 | E10: 2024-01-31 | F10: 182 | G10: 174 | H10: 8 | I10: 0.0433 | J10: 1 | K10: 6293.56 | L10: 1124.69 | M10: 738.92 | N10: 1153.73 | O10: 9310.9 | P10: 6481.75 | Q10: 1078.13 | R10: 769.45 | S10: 1153.73 | T10: 9483.06 | U10: 188.19 | V10: -46.56 | W10: 30.53 | X10: 0 | Y10: 172.16 | Z10: 2024-01
A11: PO-1000010 | B11: 1000 | C11: SKU-2002 | D11: 2024-06-10 | E11: 2024-06-12 | F11: 661 | G11: 635 | H11: 26 | I11: 0.0379 | J11: 1 | K11: 23244.06 | L11: 4084.72 | M11: 2683.66 | N11: 4190.21 | O11: 34202.65 | P11: 24727.3 | Q11: 4124.14 | R11: 2620.56 | S11: 4190.21 | T11: 35662.21 | U11: 1483.24 | V11: 39.42 | W11: -63.1 | X11: 0 | Y11: 1459.56 | Z11: 2024-06
A12: PO-1000011 | B12: 1000 | C12: SKU-1003 | D12: 2024-10-14 | E12: 2024-10-17 | F12: 748 | G12: 731 | H12: 17 | I12: 0.0223 | J12: 1 | K12: 21635.9 | L12: 4622.34 | M12: 3036.88 | N12: 4741.72 | O12: 34036.84 | P12: 22333.36 | Q12: 4608.75 | R12: 3187.91 | S12: 4741.72 | T12: 34871.74 | U12: 697.46 | V12: -13.59 | W12: 151.03 | X12: 0 | Y12: 834.9 | Z12: 2024-10
A13: PO-1000012 | B13: 1000 | C13: SKU-1002 | D13: 2024-09-09 | E13: 2024-09-10 | F13: 198 | G13: 191 | H13: 7 | I13: 0.0345 | J13: 1 | K13: 6023.16 | L13: 1223.56 | M13: 803.88 | N13: 1255.16 | O13: 9305.76 | P13: 6069.94 | Q13: 1187.83 | R13: 818.39 | S13: 1255.16 | T13: 9331.32 | U13: 46.78 | V13: -35.73 | W13: 14.51 | X13: 0 | Y13: 25.56 | Z13: 2024-09
... A2501: PO-1002500 | B2501: 1000 | C2501: SKU-4518 | D2501: 2024-08-27 | E2501: 2024-08-29 | F2501: 547 | G2501: 483 | H2501: 64 | I2501: 0.1154 | J2501: 2 | K2501: 21972.99 | L2501: 3380.24 | M2501: 2220.82 | N2501: 3467.54 | O2501: 31041.59 | P2501: 23433.44 | Q2501: 4538.76 | R2501: 2797.93 | S2501: 3467.54 | T2501: 34237.67 | U2501: 1460.45 | V2501: 1158.52 | W2501: 577.11 | X2501: 0 | Y2501: 3196.07 | Z2501: 2024-08

Sheet RAW_Material_Movements
A1: Document_Number | B1: Movement_Type | C1: Movement_Date | D1: Plant | E1: Production_Order | F1: Material | G1: Material_Description | H1: Quantity | I1: Unit | J1: Standard_Price | K1: Actual_Price | L1: Standard_Value | M1: Actual_Value | N1: Price_Variance | O1: Quantity_Variance
A2: MD-5000001 | B2: 261 | C2: 2024-01-13 | D2: 1000 | E2: PO-1000001 | F2: PAPERBOARD-GR-A | G2: Paperboard Gr A | H2: 19.5194 | I2: TON | J2: 780 | K2: 814.33 | L2: 14976 | M2: 15895.21 | N2: 670.1 | O2: 249.11
A3: MD-5000002 | B3: 261 | C3: 2024-01-13 | D3: 1000 | E3: PO-1000001 | F3: PAPERBOARD-GR-B | G3: Paperboard Gr B | H3: 4.9344 | I3: TON | J3: 720 | K3: 720.47 | L3: 3456 | M3: 3555.08 | N3: 2.3 | O3: 96.78
A4: MD-5000003 | B4: 261 | C4: 2024-01-13 | D4: 1000 | E4: PO-1000001 | F4: INK-BASIC-4COLOR | G4: Ink Basic 4Color | H4: 0.3327 | I4: GAL | J4: 2400 | K4: 2215.03 | L4: 768 | M4: 736.88 | N4: -61.53 | O4: 30.42
A5: MD-5000004 | B5: 261 | C5: 2024-01-13 | D5: 1000 | E5: PO-1000001 | F5: INK-SPECIALTY | G5: Ink Specialty | H5: 0.1259 | I5: GAL | J5: 4200 | K5: 5032.58 | L5: 504 | M5: 633.75 | N5: 104.85 | O5: 24.9
A6: MD-5000005 | B6: 261 | C6: 2024-01-13 | D6: 1000 | E6: PO-1000001 | F6: COATING-STD | G6: Coating Std | H6: 0.1641 | I6: GAL | J6: 3100 | K6: 3722.92 | L6: 496 | M6: 611.01 | N6: 102.23 | O6: 12.77
A7: MD-5000006 | B7: 261 | C7: 2024-01-16 | D7: 1000 | E7: PO-1000002 | F7: PAPERBOARD-GR-A | G7: Paperboard Gr A | H7: 17.2128 | I7: TON | J7: 780 | K7: 786.12 | L7: 13092.3 | M7: 13531.42 | N7: 105.41 | O7: 333.71
A8: MD-5000007 | B8: 261 | C8: 2024-01-16 | D8: 1000 | E8: PO-1000002 | F8: PAPERBOARD-GR-B | G8: Paperboard Gr B | H8: 3.863 | I8: TON | J8: 720 | K8: 698.9 | L8: 2685.6 | M8: 2699.86 | N8: -81.52 | O8: 95.78
A9: MD-5000008 | B9: 261 | C9: 2024-01-16 | D9: 1000 | E9: PO-1000002 | F9: INK-BASIC-4COLOR | G9: Ink Basic 4Color | H9: 0.4468 | I9: GAL | J9: 2400 | K9: 2199.57 | L9: 1074.24 | M9: 982.81 | N9: -89.56 | O9: -1.88
A10: MD-5000009 | B10: 261 | C10: 2024-01-16 | D10: 1000 | E10: PO-1000002 | F10: COATING-STD | G10: Coating Std | H10: 0.1163 | I10: GAL | J10: 3100 | K10: 3693.41 | L10: 346.89 | M10: 429.38 | N10: 68.99 | O10: 13.5
A11: MD-5000010 | B11: 261 | C11: 2024-08-17 | D11: 1000 | E11: PO-1000003 | F11: PAPERBOARD-GR-A | G11: Paperboard Gr A | H11: 7.033 | I11: TON | J11: 780 | K11: 827.96 | L11: 5475.6 | M11: 5823.11 | N11: 337.33 | O11: 10.18
A12: MD-5000011 | B12: 261 | C12: 2024-08-17 | D12: 1000 | E12: PO-1000003 | F12: PAPERBOARD-GR-B | G12: Paperboard Gr B | H12: 1.5902 | I12: TON | J12: 720 | K12: 717.77 | L12: 1123.2 | M12: 1141.41 | N12: -3.55 | O12: 21.75
A13: MD-5000012 | B13: 261 | C13: 2024-08-17 | D13: 1000 | E13: PO-1000003 | F13: INK-BASIC-4COLOR | G13: Ink Basic 4Color | H13: 0.1914 | I13: GAL | J13: 2400 | K13: 2184.09 | L13: 449.28 | M13: 418.14 | N13: -41.34 | O13: 10.19
... A11230: MD-5011229 | B11230: 261 | C11230: 2024-08-27 | D11230: 1000 | E11230: PO-1002500 | F11230: COATING-STD | G11230: Coating Std | H11230: 0.3585 | I11230: GAL | J11230: 3100 | K11230: 3784.77 | L11230: 1017.42 | M11230: 1356.95 | N11230: 245.51 | O11230: 94.02

Sheet RAW_Purchase_Orders
A1: PO_Number | B1: PO_Date | C1: Vendor | D1: Plant | E1: Material | F1: Material_Description | G1: Quantity | H1: Unit | I1: Standard_Price | J1: Actual_Price | K1: Standard_Value | L1: Actual_Value | M1: PPV | N1: PPV_Pct
A2: PO-4500001 | B2: 2023-12-29 | C2: VENDOR-1020 | D2: 1000 | E2: PAPERBOARD-GR-A | F2: Paperboard Gr A | G2: 146 | H2: TON | I2: 780 | J2: 840.75 | K2: 113880 | L2: 122749.54 | M2: 8869.54 | N2: 7.79
A3: PO-4500002 | B3: 2024-01-15 | C3: VENDOR-1006 | D3: 1000 | E3: PAPERBOARD-GR-A | F3: Paperboard Gr A | G3: 95 | H3: TON | I3: 780 | J3: 802.38 | K3: 74100 | L3: 76226.53 | M3: 2126.53 | N3: 2.87
A4: PO-4500003 | B4: 2024-02-04 | C4: VENDOR-1002 | D4: 1000 | E4: PAPERBOARD-GR-A | F4: Paperboard Gr A | G4: 118 | H4: TON | I4: 780 | J4: 829 | K4: 92040 | L4: 97822.12 | M4: 5782.12 | N4: 6.28
A5: PO-4500004 | B5: 2024-02-14 | C5: VENDOR-1003 | D5: 1000 | E5: PAPERBOARD-GR-A | F5: Paperboard Gr A | G5: 194 | H5: TON | I5: 780 | J5: 812.19 | K5: 151320 | L5: 157564.29 | M5: 6244.29 | N5: 4.13
A6: PO-4500005 | B6: 2024-02-29 | C6: VENDOR-1011 | D6: 1000 | E6: PAPERBOARD-GR-A | F6: Paperboard Gr A | G6: 100 | H6: TON | I6: 780 | J6: 828.92 | K6: 78000 | L6: 82891.86 | M6: 4891.86 | N6: 6.27
A7: PO-4500006 | B7: 2024-03-16 | C7: VENDOR-1001 | D7: 1000 | E7: PAPERBOARD-GR-A | F7: Paperboard Gr A | G7: 119 | H7: TON | I7: 780 | J7: 823.85 | K7: 92820 | L7: 98038.05 | M7: 5218.05 | N7: 5.62
A8: PO-4500007 | B8: 2024-04-05 | C8: VENDOR-1012 | D8: 1000 | E8: PAPERBOARD-GR-A | F8: Paperboard Gr A | G8: 131 | H8: TON | I8: 780 | J8: 815.2 | K8: 102180 | L8: 106791.4 | M8: 4611.4 | N8: 4.51
A9: PO-4500008 | B9: 2024-04-13 | C9: VENDOR-1017 | D9: 1000 | E9: PAPERBOARD-GR-A | F9: Paperboard Gr A | G9: 119 | H9: TON | I9: 780 | J9: 837.12 | K9: 92820 | L9: 99617.6 | M9: 6797.6 | N9: 7.32
A10: PO-4500009 | B10: 2024-05-01 | C10: VENDOR-1009 | D10: 1000 | E10: PAPERBOARD-GR-A | F10: Paperboard Gr A | G10: 143 | H10: TON | I10: 780 | J10: 809.32 | K10: 111540 | L10: 115732.73 | M10: 4192.73 | N10: 3.76
A11: PO-4500010 | B11: 2024-05-11 | C11: VENDOR-1015 | D11: 1000 | E11: PAPERBOARD-GR-A | F11: Paperboard Gr A | G11: 179 | H11: TON | I11: 780 | J11: 814.66 | K11: 139620 | L11: 145823.73 | M11: 6203.73 | N11: 4.44
A12: PO-4500011 | B12: 2024-06-06 | C12: VENDOR-1000 | D12: 1000 | E12: PAPERBOARD-GR-A | F12: Paperboard Gr A | G12: 168 | H12: TON | I12: 780 | J12: 823.36 | K12: 131040 | L12: 138325.04 | M12: 7285.04 | N12: 5.56
A13: PO-4500012 | B13: 2024-06-14 | C13: VENDOR-1014 | D13: 1000 | E13: PAPERBOARD-GR-A | F13: Paperboard Gr A | G13: 127 | H13: TON | I13: 780 | J13: 812.78 | K13: 99060 | L13: 103223.24 | M13: 4163.24 | N13: 4.2
... A121: PO-4500120 | B121: 2024-12-10 | C121: VENDOR-1010 | D121: 1000 | E121: COATING-STD | F121: Coating Std | G121: 520 | H121: GAL | I121: 3100 | J121: 3909.16 | K121: 1612000 | L121: 2032763.1 | M121: 420763.13 | N121: 26.1

Sheet RAW_Cost_Center
A1: Period | B1: Period_Start | C1: Cost_Center | D1: Cost_Center_Name | E1: Cost_Element | F1: Cost_Element_Name | G1: Budget | H1: Actual | I1: Variance | J1: Variance_Pct
A2: 01/2024 | B2: 2024-01-01 | C2: CC-1000-PROD-L1 | D2: Production Line 1 | E2: 400000 | F2: Materials | G2: 90000 | H2: 85017.4 | I2: -4982.6 | J2: -5.5
A3: 01/2024 | B3: 2024-01-01 | C3: CC-1000-PROD-L1 | D3: Production Line 1 | E3: 410000 | F3: Direct Labor | G3: 36000 | H3: 35411.88 | I3: -588.12 | J3: -1.6
A4: 01/2024 | B4: 2024-01-01 | C4: CC-1000-PROD-L1 | D4: Production Line 1 | E4: 420000 | F4: Indirect Labor | G4: 16000 | H4: 15061.96 | I4: -938.04 | J4: -5.9
A5: 01/2024 | B5: 2024-01-01 | C5: CC-1000-PROD-L1 | D5: Production Line 1 | E5: 430000 | F5: Energy | G5: 24000 | H5: 22634.55 | I5: -1365.45 | J5: -5.7
A6: 01/2024 | B6: 2024-01-01 | C6: CC-1000-PROD-L1 | D6: Production Line 1 | E6: 440000 | F6: Maintenance | G6: 14000 | H6: 13233.28 | I6: -766.72 | J6: -5.5
A7: 01/2024 | B7: 2024-01-01 | C7: CC-1000-PROD-L1 | D7: Production Line 1 | E7: 450000 | F7: Depreciation | G7: 12000 | H7: 11829.42 | I7: -170.58 | J7: -1.4
A8: 01/2024 | B8: 2024-01-01 | C8: CC-1000-PROD-L1 | D8: Production Line 1 | E8: 460000 | F8: Supplies | G8: 8000 | H8: 8456 | I8: 456 | J8: 5.7
A9: 01/2024 | B9: 2024-01-01 | C9: CC-1000-PROD-L2 | D9: Production Line 2 | E9: 400000 | F9: Materials | G9: 90000 | H9: 96794.67 | I9: 6794.67 | J9: 7.5
A10: 01/2024 | B10: 2024-01-01 | C10: CC-1000-PROD-L2 | D10: Production Line 2 | E10: 410000 | F10: Direct Labor | G10: 36000 | H10: 40034.21 | I10: 4034.21 | J10: 11.2
A11: 01/2024 | B11: 2024-01-01 | C11: CC-1000-PROD-L2 | D11: Production Line 2 | E11: 420000 | F11: Indirect Labor | G11: 16000 | H11: 14725.07 | I11: -1274.93 | J11: -8
A12: 01/2024 | B12: 2024-01-01 | C12: CC-1000-PROD-L2 | D12: Production Line 2 | E12: 430000 | F12: Energy | G12: 24000 | H12: 34971.51 | I12: 10971.51 | J12: 45.7
A13: 01/2024 | B13: 2024-01-01 | C13: CC-1000-PROD-L2 | D13: Production Line 2 | E13: 440000 | F13: Maintenance | G13: 14000 | H13: 14304.67 | I13: 304.67 | J13: 2.2
... A505: 12/2024 | B505: 2024-12-01 | C505: CC-1000-ADMIN | D505: Plant Administration | E505: 460000 | F505: Supplies | G505: 600 | H505: 583.24 | I505: -16.76 | J505: -2.8

Sheet RAW_Energy
A1: Date | B1: Production_Line | C1: Production_000s | D1: kWh_Consumed | E1: kWh_per_1000 | F1: Energy_Cost | G1: Downtime_Pct | H1: Run_Hours
A2: 2024-01-01 | B2: 1 | C2: 919 | D2: 2001.9 | E2: 2.178 | F2: 164.16 | G2: 0.059 | H2: 22.6
A3: 2024-01-01 | B3: 2 | C3: 1210 | D3: 3538.9 | E3: 2.925 | F3: 290.19 | G3: 0.128 | H3: 20.9
A4: 2024-01-02 | B4: 1 | C4: 1228 | D4: 2746.5 | E4: 2.237 | F4: 225.21 | G4: 0.061 | H4: 22.5
A5: 2024-01-02 | B5: 2 | C5: 913 | D5: 2927.2 | E5: 3.206 | F5: 240.03 | G5: 0.14 | H5: 20.7
A6: 2024-01-03 | B6: 1 | C6: 820 | D6: 1764.4 | E6: 2.152 | F6: 144.68 | G6: 0.04 | H6: 23
A7: 2024-01-03 | B7: 2 | C7: 1045 | D7: 3237.6 | E7: 3.098 | F7: 265.48 | G7: 0.132 | H7: 20.8
A8: 2024-01-04 | B8: 1 | C8: 984 | D8: 2139.1 | E8: 2.174 | F8: 175.41 | G8: 0.074 | H8: 22.2
A9: 2024-01-04 | B9: 2 | C9: 1288 | D9: 3898.4 | E9: 3.027 | F9: 319.66 | G9: 0.114 | H9: 21.3
A10: 2024-01-05 | B10: 1 | C10: 1221 | D10: 2487.7 | E10: 2.037 | F10: 203.99 | G10: 0.066 | H10: 22.4
A11: 2024-01-05 | B11: 2 | C11: 1034 | D11: 3286.8 | E11: 3.179 | F11: 269.52 | G11: 0.094 | H11: 21.7
A12: 2024-01-06 | B12: 1 | C12: 498 | D12: 1075.9 | E12: 2.16 | F12: 88.22 | G12: 0.089 | H12: 21.9
A13: 2024-01-06 | B13: 2 | C13: 222 | D13: 671.9 | E13: 3.027 | F13: 55.1 | G13: 0.129 | H13: 20.9
... A731: 2024-12-30 | B731: 2 | C731: 862 | D731: 2665.9 | E731: 3.093 | F731: 218.6 | G731: 0.131 | H731: 20.9

Sheet MASTER_SKU
A1: SKU | B1: Description | C1: Product_Group | D1: Complexity | E1: Primary_Line | F1: Annual_Volume_000s | G1: Standard_Cost_per_1000 | H1: Revenue_per_1000 | I1: Standard_Gross_Margin | J1: Standard_GM_Pct | K1: Base_Scrap_Rate | L1: BOM_Complexity
A2: SKU-1001 | B2: Carton Blank - SKU-1001 | C2: CARTON-BLANK | D2: LOW | E2: 1 | F2: 85000 | G2: 45.2 | H2: 58.5 | I2: 13.3 | J2: 22.7 | K2: 0.025 | L2: low
A3: SKU-1002 | B3: Carton Blank - SKU-1002 | C3: CARTON-BLANK | D3: LOW | E3: 1 | F3: 72000 | G3: 46.8 | H3: 60.2 | I3: 13.4 | J3: 22.3 | K3: 0.028 | L3: low
A4: SKU-1003 | B4: Carton Blank - SKU-1003 | C4: CARTON-BLANK | D4: LOW | E4: 1 | F4: 68000 | G4: 44.5 | H4: 57.8 | I4: 13.3 | J4: 23 | K4: 0.022 | L4: low
A5: SKU-1004 | B5: Carton Blank - SKU-1004 | C5: CARTON-BLANK | D5: LOW | E5: 2 | F5: 55000 | G5: 47.9 | H5: 61.5 | I5: 13.6 | J5: 22.1 | K5: 0.03 | L5: low
A6: SKU-1005 | B6: Carton Blank - SKU-1005 | C6: CARTON-BLANK | D6: LOW | E6: 2 | F6: 48000 | G6: 45.6 | H6: 59 | I6: 13.4 | J6: 22.7 | K6: 0.026 | L6: low
A7: SKU-2001 | B7: Carton Blank - SKU-2001 | C7: CARTON-BLANK | D7: MEDIUM | E7: 1 | F7: 32000 | G7: 52.3 | H7: 67 | I7: 14.7 | J7: 21.9 | K7: 0.035 | L7: medium
A8: SKU-2002 | B8: Carton Blank - SKU-2002 | C8: CARTON-BLANK | D8: MEDIUM | E8: 1 | F8: 28000 | G8: 54.1 | H8: 69.5 | I8: 15.4 | J8: 22.2 | K8: 0.038 | L8: medium
A9: SKU-2003 | B9: Carton Blank - SKU-2003 | C9: CARTON-BLANK | D9: MEDIUM | E9: 2 | F9: 25000 | G9: 51.8 | H9: 66.2 | I9: 14.4 | J9: 21.8 | K9: 0.032 | L9: medium
A10: SKU-2004 | B10: Carton Blank - SKU-2004 | C10: CARTON-BLANK | D10: MEDIUM | E10: 2 | F10: 22000 | G10: 55.4 | H10: 71 | I10: 15.6 | J10: 22 | K10: 0.04 | L10: medium
A11: SKU-2005 | B11: Carton Blank - SKU-2005 | C11: CARTON-BLANK | D11: MEDIUM | E11: 1 | F11: 18000 | G11: 53.2 | H11: 68.5 | I11: 15.3 | J11: 22.3 | K11: 0.036 | L11: medium
A12: SKU-4421 | B12: Carton Blank - SKU-4421 | C12: CARTON-BLANK | D12: HIGH | E12: 2 | F12: 42000 | G12: 58.5 | H12: 68 | I12: 9.5 | J12: 14 | K12: 0.094 | L12: high
A13: SKU-4455 | B13: Carton Blank - SKU-4455 | C13: CARTON-BLANK | D13: HIGH | E13: 2 | F13: 38000 | G13: 57.2 | H13: 66.5 | I13: 9.3 | J13: 14 | K13: 0.088 | L13: high
... A25: SKU-5801 | B25: Carton Blank - SKU-5801 | C25: CARTON-BLANK | D25: LOW | E25: 1 | F25: 3600 | G25: 67.2 | H25: 77.5 | I25: 10.3 | J25: 13.3 | K25: 0.045 | L25: low

Sheet MASTER_Materials
A1: Material | B1: Description | C1: Material_Type | D1: Material_Group | E1: Base_Unit | F1: Standard_Price | G1: Price_Unit | H1: Valuation_Class | I1: Price_Control
A2: PAPERBOARD-GR-A | B2: Paperboard Gr A | C2: ROH | D2: RAW-MATERIALS | E2: TON | F2: 780 | G2: 1 | H2: 3000 | I2: S
A3: PAPERBOARD-GR-B | B3: Paperboard Gr B | C3: ROH | D3: RAW-MATERIALS | E3: TON | F3: 720 | G3: 1 | H3: 3000 | I3: S
A4: INK-BASIC-4COLOR | B4: Ink Basic 4Color | C4: ROH | D4: RAW-MATERIALS | E4: GAL | F4: 2400 | G4: 1 | H4: 3000 | I4: S
A5: INK-SPECIALTY | B5: Ink Specialty | C5: ROH | D5: RAW-MATERIALS | E5: GAL | F5: 4200 | G5: 1 | H5: 3000 | I5: S
A6: COATING-STD | B6: Coating Std | C6: ROH | D6: RAW-MATERIALS | E6: GAL | F6: 3100 | G6: 1 | H6: 3000 | I6: S

Sheet ANALYSIS_PPV
A1: PURCHASE PRICE VARIANCE ANALYSIS
A3: Commodity-Level PPV (FY 2024)
A5: Material | B5: Quantity | C5: Std_Price | D5: Avg_Actual_Price | E5: Std_Value | F5: Actual_Value | G5: PPV | H5: PPV_%
A6: PAPERBOARD-GR-A | B6: =SUMIF(RAW_Purchase_Orders!E:E,A6,RAW_Purchase_Orders!G:G) -> 3213 | C6: =VLOOKUP(A6,MASTER_Materials!A:F,6,FALSE()) -> 780 | D6: =IF(B6=0,0,SUMIF(RAW_Purchase_Orders!E:E,A6,RAW_Purchase_Orders!L:L)/B6) -> 831.41041 | E6: =B6*C6 -> 2506140 | F6: =SUMIF(RAW_Purchase_Orders!E:E,A6,RAW_Purchase_Orders!L:L) -> 2671321.6 | G6: =F6-E6 -> 165181.64 | H6: =IF(E6=0,0,G6/E6) -> 0.065910779
A7: PAPERBOARD-GR-B | B7: =SUMIF(RAW_Purchase_Orders!E:E,A7,RAW_Purchase_Orders!G:G) -> 3296 | C7: =VLOOKUP(A7,MASTER_Materials!A:F,6,FALSE()) -> 720 | D7: =IF(B7=0,0,SUMIF(RAW_Purchase_Orders!E:E,A7,RAW_Purchase_Orders!L:L)/B7) -> 729.28514 | E7: =B7*C7 -> 2373120 | F7: =SUMIF(RAW_Purchase_Orders!E:E,A7,RAW_Purchase_Orders!L:L) -> 2403723.8 | G7: =F7-E7 -> 30603.82 | H7: =IF(E7=0,0,G7/E7) -> 0.012896027
A8: INK-BASIC-4COLOR | B8: =SUMIF(RAW_Purchase_Orders!E:E,A8,RAW_Purchase_Orders!G:G) -> 36177 | C8: =VLOOKUP(A8,MASTER_Materials!A:F,6,FALSE()) -> 2400 | D8: =IF(B8=0,0,SUMIF(RAW_Purchase_Orders!E:E,A8,RAW_Purchase_Orders!L:L)/B8) -> 2280.0734 | E8: =B8*C8 -> 86824800 | F8: =SUMIF(RAW_Purchase_Orders!E:E,A8,RAW_Purchase_Orders!L:L) -> 82486215 | G8: =F8-E8 -> -4338585.2 | H8: =IF(E8=0,0,G8/E8) -> -0.049969424
A9: INK-SPECIALTY | B9: =SUMIF(RAW_Purchase_Orders!E:E,A9,RAW_Purchase_Orders!G:G) -> 28312 | C9: =VLOOKUP(A9,MASTER_Materials!A:F,6,FALSE()) -> 4200 | D9: =IF(B9=0,0,SUMIF(RAW_Purchase_Orders!E:E,A9,RAW_Purchase_Orders!L:L)/B9) -> 5260.2607 | E9: =B9*C9 -> 118910400 | F9: =SUMIF(RAW_Purchase_Orders!E:E,A9,RAW_Purchase_Orders!L:L) -> 1.489285e+08 | G9: =F9-E9 -> 30018101 | H9: =IF(E9=0,0,G9/E9) -> 0.25244303
A10: COATING-STD | B10: =SUMIF(RAW_Purchase_Orders!E:E,A10,RAW_Purchase_Orders!G:G) -> 12271 | C10: =VLOOKUP(A10,MASTER_Materials!A:F,6,FALSE()) -> 3100 | D10: =IF(B10=0,0,SUMIF(RAW_Purchase_Orders!E:E,A10,RAW_Purchase_Orders!L:L)/B10) -> 3782.1288 | E10: =B10*C10 -> 38040100 | F10: =SUMIF(RAW_Purchase_Orders!E:E,A10,RAW_Purchase_Orders!L:L) -> 46410502 | G10: =F10-E10 -> 8370402.5 | H10: =IF(E10=0,0,G10/E10) -> 0.22004155
A11: TOTAL | B11: =SUM(B6:B10) -> 83269 | E11: =SUM(E6:E10) -> 248654560 | F11: =SUM(F6:F10) -> 2.8290026e+08 | G11: =SUM(G6:G10) -> 34245704 | H11: =IF(E11=0,0,G11/E11) -> 0.13772401
A14: RECOVERY ASSUMPTIONS
A15: Std Cost Update Capture Rate: | B15: 0.022 | C15: (% of unfavorable PPV addressable via standard cost updates)
A17: Addressable Unfavorable PPV: | B17: =SUMIF(G6:G10,">0",G6:G10) -> 38584289
A18: Standard Cost Refresh Opportunity: | B18: =B17*B15 -> 848854.37

Sheet ANALYSIS_Scrap
A1: SKU-LEVEL SCRAP ANALYSIS | M1: TCOQ Multiplier: | N1: 2.4
A3: Scrap Rate by SKU (sorted by complexity impact)
A5: SKU | B5: Planned_Qty | C5: Good_Qty | D5: Scrap_Qty | E5: Scrap_Rate | F5: Std_Cost | G5: Actual_Cost | H5: Variance | I5: Scrap_$ | J5: TCOQ_Mult | K5: True_Scrap_Cost | L5: Complexity
A6: SKU-4801 | B6: =SUMIF(RAW_Production_Orders!C:C,A6,RAW_Production_Orders!F:F) -> 20057 | C6: =SUMIF(RAW_Production_Orders!C:C,A6,RAW_Production_Orders!G:G) -> 17402 | D6: =SUMIF(RAW_Production_Orders!C:C,A6,RAW_Production_Orders!H:H) -> 2655 | E6: =IF(B6=0,0,D6/B6) -> 0.13237274 | F6: =SUMIF(RAW_Production_Orders!C:C,A6,RAW_Production_Orders!O:O) -> 1104314.4 | G6: =SUMIF(RAW_Production_Orders!C:C,A6,RAW_Production_Orders!T:T) -> 1199357.7 | H6: =G6-F6 -> 95043.32 | I6: =D6*IFERROR(VLOOKUP(A6,MASTER_SKU!A:G,7,FALSE()),0) -> 157176 | J6: =$N$1 -> 2.4 | K6: =I6*J6 -> 377222.4 | L6: =IFERROR(VLOOKUP(A6,MASTER_SKU!A:D,4,FALSE()),"") -> HIGH
A7: SKU-4512 | B7: =SUMIF(RAW_Production_Orders!C:C,A7,RAW_Production_Orders!F:F) -> 41333 | C7: =SUMIF(RAW_Production_Orders!C:C,A7,RAW_Production_Orders!G:G) -> 36630 | D7: =SUMIF(RAW_Production_Orders!C:C,A7,RAW_Production_Orders!H:H) -> 4703 | E7: =IF(B7=0,0,D7/B7) -> 0.11378318 | F7: =SUMIF(RAW_Production_Orders!C:C,A7,RAW_Production_Orders!O:O) -> 2361718 | G7: =SUMIF(RAW_Production_Orders!C:C,A7,RAW_Production_Orders!T:T) -> 2566507.7 | H7: =G7-F7 -> 204789.73 | I7: =D7*IFERROR(VLOOKUP(A7,MASTER_SKU!A:G,7,FALSE()),0) -> 293467.2 | J7: =$N$1 -> 2.4 | K7: =I7*J7 -> 704321.28 | L7: =IFERROR(VLOOKUP(A7,MASTER_SKU!A:D,4,FALSE()),"") -> HIGH
A8: SKU-4518 | B8: =SUMIF(RAW_Production_Orders!C:C,A8,RAW_Production_Orders!F:F) -> 47311 | C8: =SUMIF(RAW_Production_Orders!C:C,A8,RAW_Production_Orders!G:G) -> 42529 | D8: =SUMIF(RAW_Production_Orders!C:C,A8,RAW_Production_Orders!H:H) -> 4782 | E8: =IF(B8=0,0,D8/B8) -> 0.10107586 | F8: =SUMIF(RAW_Production_Orders!C:C,A8,RAW_Production_Orders!O:O) -> 2684842.5 | G8: =SUMIF(RAW_Production_Orders!C:C,A8,RAW_Production_Orders!T:T) -> 2898346.8 | H8: =G8-F8 -> 213504.28 | I8: =D8*IFERROR(VLOOKUP(A8,MASTER_SKU!A:G,7,FALSE()),0) -> 295527.6 | J8: =$N$1 -> 2.4 | K8: =I8*J8 -> 709266.24 | L8: =IFERROR(VLOOKUP(A8,MASTER_SKU!A:D,4,FALSE()),"") -> HIGH
A9: SKU-4421 | B9: =SUMIF(RAW_Production_Orders!C:C,A9,RAW_Production_Orders!F:F) -> 80136 | C9: =SUMIF(RAW_Production_Orders!C:C,A9,RAW_Production_Orders!G:G) -> 72084 | D9: =SUMIF(RAW_Production_Orders!C:C,A9,RAW_Production_Orders!H:H) -> 8052 | E9: =IF(B9=0,0,D9/B9) -> 0.10047919 | F9: =SUMIF(RAW_Production_Orders!C:C,A9,RAW_Production_Orders!O:O) -> 4375730.1 | G9: =SUMIF(RAW_Production_Orders!C:C,A9,RAW_Production_Orders!T:T) -> 4719667.3 | H9: =G9-F9 -> 343937.14 | I9: =D9*IFERROR(VLOOKUP(A9,MASTER_SKU!A:G,7,FALSE()),0) -> 471042 | J9: =$N$1 -> 2.4 | K9: =I9*J9 -> 1130500.8 | L9: =IFERROR(VLOOKUP(A9,MASTER_SKU!A:D,4,FALSE()),"") -> HIGH
A10: SKU-4455 | B10: =SUMIF(RAW_Production_Orders!C:C,A10,RAW_Production_Orders!F:F) -> 68893 | C10: =SUMIF(RAW_Production_Orders!C:C,A10,RAW_Production_Orders!G:G) -> 62426 | D10: =SUMIF(RAW_Production_Orders!C:C,A10,RAW_Production_Orders!H:H) -> 6467 | E10: =IF(B10=0,0,D10/B10) -> 0.093870205 | F10: =SUMIF(RAW_Production_Orders!C:C,A10,RAW_Production_Orders!O:O) -> 3703605 | G10: =SUMIF(RAW_Production_Orders!C:C,A10,RAW_Production_Orders!T:T) -> 3999968.5 | H10: =G10-F10 -> 296363.49 | I10: =D10*IFERROR(VLOOKUP(A10,MASTER_SKU!A:G,7,FALSE()),0) -> 369912.4 | J10: =$N$1 -> 2.4 | K10: =I10*J10 -> 887789.76 | L10: =IFERROR(VLOOKUP(A10,MASTER_SKU!A:D,4,FALSE()),"") -> HIGH
A11: SKU-4672 | B11: =SUMIF(RAW_Production_Orders!C:C,A11,RAW_Production_Orders!F:F) -> 30612 | C11: =SUMIF(RAW_Production_Orders!C:C,A11,RAW_Production_Orders!G:G) -> 27889 | D11: =SUMIF(RAW_Production_Orders!C:C,A11,RAW_Production_Orders!H:H) -> 2723 | E11: =IF(B11=0,0,D11/B11) -> 0.088952045 | F11: =SUMIF(RAW_Production_Orders!C:C,A11,RAW_Production_Orders!O:O) -> 1637705.3 | G11: =SUMIF(RAW_Production_Orders!C:C,A11,RAW_Production_Orders!T:T) -> 1743026.4 | H11: =G11-F11 -> 105321.16 | I11: =D11*IFERROR(VLOOKUP(A11,MASTER_SKU!A:G,7,FALSE()),0) -> 154666.4 | J11: =$N$1 -> 2.4 | K11: =I11*J11 -> 371199.36 | L11: =IFERROR(VLOOKUP(A11,MASTER_SKU!A:D,4,FALSE()),"") -> HIGH
A12: SKU-5678 | B12: =SUMIF(RAW_Production_Orders!C:C,A12,RAW_Production_Orders!F:F) -> 6577 | C12: =SUMIF(RAW_Production_Orders!C:C,A12,RAW_Production_Orders!G:G) -> 6108 | D12: =SUMIF(RAW_Production_Orders!C:C,A12,RAW_Production_Orders!H:H) -> 469 | E12: =IF(B12=0,0,D12/B12) -> 0.071309107 | F12: =SUMIF(RAW_Production_Orders!C:C,A12,RAW_Production_Orders!O:O) -> 414704.85 | G12: =SUMIF(RAW_Production_Orders!C:C,A12,RAW_Production_Orders!T:T) -> 441725.61 | H12: =G12-F12 -> 27020.76 | I12: =D12*IFERROR(VLOOKUP(A12,MASTER_SKU!A:G,7,FALSE()),0) -> 33533.5 | J12: =$N$1 -> 2.4 | K12: =I12*J12 -> 80480.4 | L12: =IFERROR(VLOOKUP(A12,MASTER_SKU!A:D,4,FALSE()),"") -> HIGH
A13: SKU-5244 | B13: =SUMIF(RAW_Production_Orders!C:C,A13,RAW_Production_Orders!F:F) -> 8833 | C13: =SUMIF(RAW_Production_Orders!C:C,A13,RAW_Production_Orders!G:G) -> 8267 | D13: =SUMIF(RAW_Production_Orders!C:C,A13,RAW_Production_Orders!H:H) -> 566 | E13: =IF(B13=0,0,D13/B13) -> 0.06407789 | F13: =SUMIF(RAW_Production_Orders!C:C,A13,RAW_Production_Orders!O:O) -> 547193.74 | G13: =SUMIF(RAW_Production_Orders!C:C,A13,RAW_Production_Orders!T:T) -> 584121.86 | H13: =G13-F13 -> 36928.12 | I13: =D13*IFERROR(VLOOKUP(A13,MASTER_SKU!A:G,7,FALSE()),0) -> 39506.8 | J13: =$N$1 -> 2.4 | K13: =I13*J13 -> 94816.32 | L13: =IFERROR(VLOOKUP(A13,MASTER_SKU!A:D,4,FALSE()),"") -> HIGH
A14: SKU-5455 | B14: =SUMIF(RAW_Production_Orders!C:C,A14,RAW_Production_Orders!F:F) -> 11623 | C14: =SUMIF(RAW_Production_Orders!C:C,A14,RAW_Production_Orders!G:G) -> 10892 | D14: =SUMIF(RAW_Production_Orders!C:C,A14,RAW_Production_Orders!H:H) -> 731 | E14: =IF(B14=0,0,D14/B14) -> 0.062892541 | F14: =SUMIF(RAW_Production_Orders!C:C,A14,RAW_Production_Orders!O:O) -> 723052.86 | G14: =SUMIF(RAW_Production_Orders!C:C,A14,RAW_Production_Orders!T:T) -> 772502.76 | H14: =G14-F14 -> 49449.9 | I14: =D14*IFERROR(VLOOKUP(A14,MASTER_SKU!A:G,7,FALSE()),0) -> 51316.2 | J14: =$N$1 -> 2.4 | K14: =I14*J14 -> 123158.88 | L14: =IFERROR(VLOOKUP(A14,MASTER_SKU!A:D,4,FALSE()),"") -> HIGH
A15: SKU-5102 | B15: =SUMIF(RAW_Production_Orders!C:C,A15,RAW_Production_Orders!F:F) -> 13570 | C15: =SUMIF(RAW_Production_Orders!C:C,A15,RAW_Production_Orders!G:G) -> 12815 | D15: =SUMIF(RAW_Production_Orders!C:C,A15,RAW_Production_Orders!H:H) -> 755 | E15: =IF(B15=0,0,D15/B15) -> 0.055637436 | F15: =SUMIF(RAW_Production_Orders!C:C,A15,RAW_Production_Orders!O:O) -> 826532.44 | G15: =SUMIF(RAW_Production_Orders!C:C,A15,RAW_Production_Orders!T:T) -> 861310.73 | H15: =G15-F15 -> 34778.29 | I15: =D15*IFERROR(VLOOKUP(A15,MASTER_SKU!A:G,7,FALSE()),0) -> 51491 | J15: =$N$1 -> 2.4 | K15: =I15*J15 -> 123578.4 | L15: =IFERROR(VLOOKUP(A15,MASTER_SKU!A:D,4,FALSE()),"") -> MEDIUM
A16: SKU-5108 | B16: =SUMIF(RAW_Production_Orders!C:C,A16,RAW_Production_Orders!F:F) -> 13773 | C16: =SUMIF(RAW_Production_Orders!C:C,A16,RAW_Production_Orders!G:G) -> 13018 | D16: =SUMIF(RAW_Production_Orders!C:C,A16,RAW_Production_Orders!H:H) -> 755 | E16: =IF(B16=0,0,D16/B16) -> 0.054817396 | F16: =SUMIF(RAW_Production_Orders!C:C,A16,RAW_Production_Orders!O:O) -> 832630.22 | G16: =SUMIF(RAW_Production_Orders!C:C,A16,RAW_Production_Orders!T:T) -> 863276.78 | H16: =G16-F16 -> 30646.56 | I16: =D16*IFERROR(VLOOKUP(A16,MASTER_SKU!A:G,7,FALSE()),0) -> 50962.5 | J16: =$N$1 -> 2.4 | K16: =I16*J16 -> 122310 | L16: =IFERROR(VLOOKUP(A16,MASTER_SKU!A:D,4,FALSE()),"") -> MEDIUM
A17: SKU-5512 | B17: =SUMIF(RAW_Production_Orders!C:C,A17,RAW_Production_Orders!F:F) -> 9809 | C17: =SUMIF(RAW_Production_Orders!C:C,A17,RAW_Production_Orders!G:G) -> 9286 | D17: =SUMIF(RAW_Production_Orders!C:C,A17,RAW_Production_Orders!H:H) -> 523 | E17: =IF(B17=0,0,D17/B17) -> 0.053318381 | F17: =SUMIF(RAW_Production_Orders!C:C,A17,RAW_Production_Orders!O:O) -> 601279.94 | G17: =SUMIF(RAW_Production_Orders!C:C,A17,RAW_Production_Orders!T:T) -> 617544.37 | H17: =G17-F17 -> 16264.43 | I17: =D17*IFERROR(VLOOKUP(A17,MASTER_SKU!A:G,7,FALSE()),0) -> 35982.4 | J17: =$N$1 -> 2.4 | K17: =I17*J17 -> 86357.76 | L17: =IFERROR(VLOOKUP(A17,MASTER_SKU!A:D,4,FALSE()),"") -> MEDIUM
... A29: SKU-1001 | B29: =SUMIF(RAW_Production_Orders!C:C,A29,RAW_Production_Orders!F:F) -> 152126 | C29: =SUMIF(RAW_Production_Orders!C:C,A29,RAW_Production_Orders!G:G) -> 147938 | D29: =SUMIF(RAW_Production_Orders!C:C,A29,RAW_Production_Orders!H:H) -> 4188 | E29: =IF(B29=0,0,D29/B29) -> 0.027529811 | F29: =SUMIF(RAW_Production_Orders!C:C,A29,RAW_Production_Orders!O:O) -> 6991528.4 | G29: =SUMIF(RAW_Production_Orders!C:C,A29,RAW_Production_Orders!T:T) -> 7135345.4 | H29: =G29-F29 -> 143817.01 | I29: =D29*IFERROR(VLOOKUP(A29,MASTER_SKU!A:G,7,FALSE()),0) -> 189297.6 | J29: =$N$1 -> 2.4 | K29: =I29*J29 -> 454314.24 | L29: =IFERROR(VLOOKUP(A29,MASTER_SKU!A:D,4,FALSE()),"") -> LOW
A30: TOTAL | B30: =SUM(B6:B29) -> 1178567 | C30: =SUM(C6:C29) -> 1119242 | D30: =SUM(D6:D29) -> 59325 | E30: =IF(B30=0,0,D30/B30) -> 0.050336553 | F30: =SUM(F6:F29) -> 59450272 | G30: =SUM(G6:G29) -> 61929385 | H30: =SUM(H6:H29) -> 2479112.3 | I30: =SUM(I6:I29) -> 3287268.1 | K30: =SUM(K6:K29) -> 7889443.4
A33: SCRAP REDUCTION ASSUMPTIONS
A34: Target Scrap Reduction (HIGH complexity): | B34: 0.12
A35: Target Scrap Reduction (MEDIUM complexity): | B35: 0.05
A37: HIGH Complexity True Scrap Cost: | B37: =SUMIF(L6:L29,"HIGH",K6:K29) -> 4478755.4
A38: MEDIUM Complexity True Scrap Cost: | B38: =SUMIF(L6:L29,"MEDIUM",K6:K29) -> 1536795.1
A40: Scrap Reduction Opportunity: | B40: =B37*B34+B38*B35 -> 614290.41

Sheet ANALYSIS_Energy
A1: ENERGY COST DRIVER ANALYSIS
A3: Production Line Comparison (FY 2024)
A5: Line | B5: Production_000s | C5: kWh_Consumed | D5: kWh_per_1000 | E5: Energy_Cost | F5: Avg_Downtime | G5: Cost_per_1000
A6: 1 | B6: =SUMIF(RAW_Energy!B:B,A6,RAW_Energy!C:C) -> 336813 | C6: =SUMIF(RAW_Energy!B:B,A6,RAW_Energy!D:D) -> 721307.5 | D6: =IF(B6=0,0,C6/B6) -> 2.1415667 | E6: =SUMIF(RAW_Energy!B:B,A6,RAW_Energy!F:F) -> 59147.2 | F6: =AVERAGEIF(RAW_Energy!B:B,A6,RAW_Energy!G:G) -> 0.065410959 | G6: =IF(B6=0,0,E6/B6) -> 0.17560842
A7: 2 | B7: =SUMIF(RAW_Energy!B:B,A7,RAW_Energy!C:C) -> 336061 | C7: =SUMIF(RAW_Energy!B:B,A7,RAW_Energy!D:D) -> 1027850.7 | D7: =IF(B7=0,0,C7/B7) -> 3.0585242 | E7: =SUMIF(RAW_Energy!B:B,A7,RAW_Energy!F:F) -> 84283.87 | F7: =AVERAGEIF(RAW_Energy!B:B,A7,RAW_Energy!G:G) -> 0.1145863 | G7: =IF(B7=0,0,E7/B7) -> 0.25079932
A10: VARIANCE ANALYSIS
A12: Line 1 kWh/1000: | B12: =D6 -> 2.1415667
A13: Line 2 kWh/1000: | B13: =D7 -> 3.0585242
A14: Efficiency Gap: | B14: =B13-B12 -> 0.91695751
A15: Gap %: | B15: =IF(B12=0,0,B14/B12) -> 0.42817136
A17: Cost per kWh ($): | B17: 0.082
A19: Annual Savings (Line 2 at Line 1 efficiency): | B19: =(D7-D6)*B7*B17 -> 25268.6
A21: Achievable % of Gap: | B21: 0.75
A22: Energy Optimization Opportunity: | B22: =B19*B21 -> 18951.45
A24: NOTE: Data-derived savings = ~$25K. Original target was $473K (aspirational).
A25: Project Multiplier (for target scenarios): | B25: 18.7
A26: Scenario Target Savings: | B26: =B22*B25 -> 354392.11

Sheet ANALYSIS_Cost_Center
A1: COST CENTER SUMMARY
A3: Cost_Center | B3: Name | C3: Budget | D3: Actual | E3: Variance | F3: Var_%
A4: CC-1000-PROD-L1 | B4: Production Line 1 | C4: =SUMIF(RAW_Cost_Center!C:C,A4,RAW_Cost_Center!G:G) -> 2400000 | D4: =SUMIF(RAW_Cost_Center!C:C,A4,RAW_Cost_Center!H:H) -> 2380379.5 | E4: =D4-C4 -> -19620.47 | F4: =IF(C4=0,0,E4/C4) -> -0.0081751958
A5: CC-1000-PROD-L2 | B5: Production Line 2 | C5: =SUMIF(RAW_Cost_Center!C:C,A5,RAW_Cost_Center!G:G) -> 2400000 | D5: =SUMIF(RAW_Cost_Center!C:C,A5,RAW_Cost_Center!H:H) -> 2591984.1 | E5: =D5-C5 -> 191984.12 | F5: =IF(C5=0,0,E5/C5) -> 0.079993383
A6: CC-1000-MAINT | B6: Maintenance | C6: =SUMIF(RAW_Cost_Center!C:C,A6,RAW_Cost_Center!G:G) -> 480000 | D6: =SUMIF(RAW_Cost_Center!C:C,A6,RAW_Cost_Center!H:H) -> 478553.82 | E6: =D6-C6 -> -1446.18 | F6: =IF(C6=0,0,E6/C6) -> -0.003012875
A7: CC-1000-QA | B7: Quality Assurance | C7: =SUMIF(RAW_Cost_Center!C:C,A7,RAW_Cost_Center!G:G) -> 360000 | D7: =SUMIF(RAW_Cost_Center!C:C,A7,RAW_Cost_Center!H:H) -> 355576.65 | E7: =D7-C7 -> -4423.35 | F7: =IF(C7=0,0,E7/C7) -> -0.012287083
A8: CC-1000-WHSE | B8: Warehouse | C8: =SUMIF(RAW_Cost_Center!C:C,A8,RAW_Cost_Center!G:G) -> 240000 | D8: =SUMIF(RAW_Cost_Center!C:C,A8,RAW_Cost_Center!H:H) -> 241664.96 | E8: =D8-C8 -> 1664.96 | F8: =IF(C8=0,0,E8/C8) -> 0.0069373333
A9: CC-1000-ADMIN | B9: Plant Administration | C9: =SUMIF(RAW_Cost_Center!C:C,A9,RAW_Cost_Center!G:G) -> 180000 | D9: =SUMIF(RAW_Cost_Center!C:C,A9,RAW_Cost_Center!H:H) -> 179345.01 | E9: =D9-C9 -> -654.99 | F9: =IF(C9=0,0,E9/C9) -> -0.0036388333
A10: TOTAL | C10: =SUM(C4:C9) -> 6060000 | D10: =SUM(D4:D9) -> 6227504.1 | E10: =SUM(E4:E9) -> 167504.09 | F10: =IF(C10=0,0,E10/C10) -> 0.027640939

Sheet ANALYSIS_Monthly_Trend
A1: MONTHLY PRODUCTION TREND
A3: Month | B3: Planned_Qty | C3: Good_Qty | D3: Scrap_Qty | E3: Std_Cost | F3: Actual_Cost | G3: Variance | H3: Scrap_Rate | I3: Var_%
A4: 2024-01 | B4: =SUMIF(RAW_Production_Orders!Z:Z,A4,RAW_Production_Orders!F:F) -> 100746 | C4: =SUMIF(RAW_Production_Orders!Z:Z,A4,RAW_Production_Orders!G:G) -> 95541 | D4: =SUMIF(RAW_Production_Orders!Z:Z,A4,RAW_Production_Orders!H:H) -> 5205 | E4: =SUMIF(RAW_Production_Orders!Z:Z,A4,RAW_Production_Orders!O:O) -> 5095920.4 | F4: =SUMIF(RAW_Production_Orders!Z:Z,A4,RAW_Production_Orders!T:T) -> 5313757.4 | G4: =F4-E4 -> 217837.06 | H4: =IF(B4=0,0,D4/B4) -> 0.051664582 | I4: =IF(E4=0,0,G4/E4) -> 0.042747344
A5: 2024-02 | B5: =SUMIF(RAW_Production_Orders!Z:Z,A5,RAW_Production_Orders!F:F) -> 87003 | C5: =SUMIF(RAW_Production_Orders!Z:Z,A5,RAW_Production_Orders!G:G) -> 82705 | D5: =SUMIF(RAW_Production_Orders!Z:Z,A5,RAW_Production_Orders!H:H) -> 4298 | E5: =SUMIF(RAW_Production_Orders!Z:Z,A5,RAW_Production_Orders!O:O) -> 4391168.5 | F5: =SUMIF(RAW_Production_Orders!Z:Z,A5,RAW_Production_Orders!T:T) -> 4565697.4 | G5: =F5-E5 -> 174528.86 | H5: =IF(B5=0,0,D5/B5) -> 0.049400595 | I5: =IF(E5=0,0,G5/E5) -> 0.039745425
A6: 2024-03 | B6: =SUMIF(RAW_Production_Orders!Z:Z,A6,RAW_Production_Orders!F:F) -> 110336 | C6: =SUMIF(RAW_Production_Orders!Z:Z,A6,RAW_Production_Orders!G:G) -> 104765 | D6: =SUMIF(RAW_Production_Orders!Z:Z,A6,RAW_Production_Orders!H:H) -> 5571 | E6: =SUMIF(RAW_Production_Orders!Z:Z,A6,RAW_Production_Orders!O:O) -> 5513061.9 | F6: =SUMIF(RAW_Production_Orders!Z:Z,A6,RAW_Production_Orders!T:T) -> 5728183.2 | G6: =F6-E6 -> 215121.36 | H6: =IF(B6=0,0,D6/B6) -> 0.050491227 | I6: =IF(E6=0,0,G6/E6) -> 0.039020306
A7: 2024-04 | B7: =SUMIF(RAW_Production_Orders!Z:Z,A7,RAW_Production_Orders!F:F) -> 88690 | C7: =SUMIF(RAW_Production_Orders!Z:Z,A7,RAW_Production_Orders!G:G) -> 84270 | D7: =SUMIF(RAW_Production_Orders!Z:Z,A7,RAW_Production_Orders!H:H) -> 4420 | E7: =SUMIF(RAW_Production_Orders!Z:Z,A7,RAW_Production_Orders!O:O) -> 4455904.6 | F7: =SUMIF(RAW_Production_Orders!Z:Z,A7,RAW_Production_Orders!T:T) -> 4648211.2 | G7: =F7-E7 -> 192306.59 | H7: =IF(B7=0,0,D7/B7) -> 0.049836509 | I7: =IF(E7=0,0,G7/E7) -> 0.043157699
A8: 2024-05 | B8: =SUMIF(RAW_Production_Orders!Z:Z,A8,RAW_Production_Orders!F:F) -> 103860 | C8: =SUMIF(RAW_Production_Orders!Z:Z,A8,RAW_Production_Orders!G:G) -> 98473 | D8: =SUMIF(RAW_Production_Orders!Z:Z,A8,RAW_Production_Orders!H:H) -> 5387 | E8: =SUMIF(RAW_Production_Orders!Z:Z,A8,RAW_Production_Orders!O:O) -> 5279455.8 | F8: =SUMIF(RAW_Production_Orders!Z:Z,A8,RAW_Production_Orders!T:T) -> 5511443 | G8: =F8-E8 -> 231987.12 | H8: =IF(B8=0,0,D8/B8) -> 0.051867899 | I8: =IF(E8=0,0,G8/E8) -> 0.043941483
A9: 2024-06 | B9: =SUMIF(RAW_Production_Orders!Z:Z,A9,RAW_Production_Orders!F:F) -> 91540 | C9: =SUMIF(RAW_Production_Orders!Z:Z,A9,RAW_Production_Orders!G:G) -> 86889 | D9: =SUMIF(RAW_Production_Orders!Z:Z,A9,RAW_Production_Orders!H:H) -> 4651 | E9: =SUMIF(RAW_Production_Orders!Z:Z,A9,RAW_Production_Orders!O:O) -> 4620885.3 | F9: =SUMIF(RAW_Production_Orders!Z:Z,A9,RAW_Production_Orders!T:T) -> 4814008.9 | G9: =F9-E9 -> 193123.64 | H9: =IF(B9=0,0,D9/B9) -> 0.05080839 | I9: =IF(E9=0,0,G9/E9) -> 0.041793645
A10: 2024-07 | B10: =SUMIF(RAW_Production_Orders!Z:Z,A10,RAW_Production_Orders!F:F) -> 109719 | C10: =SUMIF(RAW_Production_Orders!Z:Z,A10,RAW_Production_Orders!G:G) -> 104184 | D10: =SUMIF(RAW_Production_Orders!Z:Z,A10,RAW_Production_Orders!H:H) -> 5535 | E10: =SUMIF(RAW_Production_Orders!Z:Z,A10,RAW_Production_Orders!O:O) -> 5534855.5 | F10: =SUMIF(RAW_Production_Orders!Z:Z,A10,RAW_Production_Orders!T:T) -> 5764612 | G10: =F10-E10 -> 229756.49 | H10: =IF(B10=0,0,D10/B10) -> 0.050447051 | I10: =IF(E10=0,0,G10/E10) -> 0.041510838
A11: 2024-08 | B11: =SUMIF(RAW_Production_Orders!Z:Z,A11,RAW_Production_Orders!F:F) -> 102573 | C11: =SUMIF(RAW_Production_Orders!Z:Z,A11,RAW_Production_Orders!G:G) -> 97259 | D11: =SUMIF(RAW_Production_Orders!Z:Z,A11,RAW_Production_Orders!H:H) -> 5314 | E11: =SUMIF(RAW_Production_Orders!Z:Z,A11,RAW_Production_Orders!O:O) -> 5217398.6 | F11: =SUMIF(RAW_Production_Orders!Z:Z,A11,RAW_Production_Orders!T:T) -> 5439869.7 | G11: =F11-E11 -> 222471.12 | H11: =IF(B11=0,0,D11/B11) -> 0.051807006 | I11: =IF(E11=0,0,G11/E11) -> 0.042640238
A12: 2024-09 | B12: =SUMIF(RAW_Production_Orders!Z:Z,A12,RAW_Production_Orders!F:F) -> 95020 | C12: =SUMIF(RAW_Production_Orders!Z:Z,A12,RAW_Production_Orders!G:G) -> 90450 | D12: =SUMIF(RAW_Production_Orders!Z:Z,A12,RAW_Production_Orders!H:H) -> 4570 | E12: =SUMIF(RAW_Production_Orders!Z:Z,A12,RAW_Production_Orders!O:O) -> 4742721.9 | F12: =SUMIF(RAW_Production_Orders!Z:Z,A12,RAW_Production_Orders!T:T) -> 4933842.3 | G12: =F12-E12 -> 191120.38 | H12: =IF(B12=0,0,D12/B12) -> 0.048095138 | I12: =IF(E12=0,0,G12/E12) -> 0.040297614
A13: 2024-10 | B13: =SUMIF(RAW_Production_Orders!Z:Z,A13,RAW_Production_Orders!F:F) -> 111947 | C13: =SUMIF(RAW_Production_Orders!Z:Z,A13,RAW_Production_Orders!G:G) -> 106417 | D13: =SUMIF(RAW_Production_Orders!Z:Z,A13,RAW_Production_Orders!H:H) -> 5530 | E13: =SUMIF(RAW_Production_Orders!Z:Z,A13,RAW_Production_Orders!O:O) -> 5640009.6 | F13: =SUMIF(RAW_Production_Orders!Z:Z,A13,RAW_Production_Orders!T:T) -> 5869590.1 | G13: =F13-E13 -> 229580.52 | H13: =IF(B13=0,0,D13/B13) -> 0.049398376 | I13: =IF(E13=0,0,G13/E13) -> 0.040705697
A14: 2024-11 | B14: =SUMIF(RAW_Production_Orders!Z:Z,A14,RAW_Production_Orders!F:F) -> 94135 | C14: =SUMIF(RAW_Production_Orders!Z:Z,A14,RAW_Production_Orders!G:G) -> 89524 | D14: =SUMIF(RAW_Production_Orders!Z:Z,A14,RAW_Production_Orders!H:H) -> 4611 | E14: =SUMIF(RAW_Production_Orders!Z:Z,A14,RAW_Production_Orders!O:O) -> 4780936.7 | F14: =SUMIF(RAW_Production_Orders!Z:Z,A14,RAW_Production_Orders!T:T) -> 4980489.2 | G14: =F14-E14 -> 199552.54 | H14: =IF(B14=0,0,D14/B14) -> 0.048982844 | I14: =IF(E14=0,0,G14/E14) -> 0.041739214
A15: 2024-12 | B15: =SUMIF(RAW_Production_Orders!Z:Z,A15,RAW_Production_Orders!F:F) -> 82998 | C15: =SUMIF(RAW_Production_Orders!Z:Z,A15,RAW_Production_Orders!G:G) -> 78765 | D15: =SUMIF(RAW_Production_Orders!Z:Z,A15,RAW_Production_Orders!H:H) -> 4233 | E15: =SUMIF(RAW_Production_Orders!Z:Z,A15,RAW_Production_Orders!O:O) -> 4177953.6 | F15: =SUMIF(RAW_Production_Orders!Z:Z,A15,RAW_Production_Orders!T:T) -> 4359680.2 | G15: =F15-E15 -> 181726.65 | H15: =IF(B15=0,0,D15/B15) -> 0.051001229 | I15: =IF(E15=0,0,G15/E15) -> 0.04349657
A16: TOTAL | B16: =SUM(B4:B15) -> 1178567 | C16: =SUM(C4:C15) -> 1119242 | D16: =SUM(D4:D15) -> 59325 | E16: =SUM(E4:E15) -> 59450272 | F16: =SUM(F4:F15) -> 61929385 | G16: =SUM(G4:G15) -> 2479112.3 | H16: =IF(B16=0,0,D16/B16) -> 0.050336553 | I16: =IF(E16=0,0,G16/E16) -> 0.041700605

Sheet ANALYSIS_Contribution
A1: TRUE CONTRIBUTION MARGIN ANALYSIS
A3: Standard vs. True Contribution by SKU
A5: SKU | B5: Complexity | C5: Revenue | D5: Std_GM | E5: Std_GM_% | F5: True_CM | G5: True_CM_% | H5: Margin_Gap | I5: Phantom?
A6: SKU-4801 | B6: =IFERROR(VLOOKUP(A6,MASTER_SKU!A:D,4,FALSE()),"") -> HIGH | C6: =SUMIF(RAW_Production_Orders!C:C,A6,RAW_Production_Orders!G:G)*IFERROR(VLOOKUP(A6,MASTER_SKU!A:H,8,FALSE()),0) -> 1192037 | D6: =SUMIF(RAW_Production_Orders!C:C,A6,RAW_Production_Orders!G:G)*IFERROR(VLOOKUP(A6,MASTER_SKU!A:I,9,FALSE()),0) -> 161838.6 | E6: =IF(C6=0,0,D6/C6) -> 0.13576642 | F6: =D6-IFERROR(VLOOKUP(A6,ANALYSIS_Scrap!A:K,11,FALSE()),0) -> -215383.8 | G6: =IF(C6=0,0,F6/C6) -> -0.1806855 | H6: =D6-F6 -> 377222.4 | I6: =IF(F6<0,"YES","") -> YES
A7: SKU-4512 | B7: =IFERROR(VLOOKUP(A7,MASTER_SKU!A:D,4,FALSE()),"") -> HIGH | C7: =SUMIF(RAW_Production_Orders!C:C,A7,RAW_Production_Orders!G:G)*IFERROR(VLOOKUP(A7,MASTER_SKU!A:H,8,FALSE()),0) -> 2637360 | D7: =SUMIF(RAW_Production_Orders!C:C,A7,RAW_Production_Orders!G:G)*IFERROR(VLOOKUP(A7,MASTER_SKU!A:I,9,FALSE()),0) -> 351648 | E7: =IF(C7=0,0,D7/C7) -> 0.13333333 | F7: =D7-IFERROR(VLOOKUP(A7,ANALYSIS_Scrap!A:K,11,FALSE()),0) -> -352673.28 | G7: =IF(C7=0,0,F7/C7) -> -0.13372209 | H7: =D7-F7 -> 704321.28 | I7: =IF(F7<0,"YES","") -> YES
A8: SKU-4518 | B8: =IFERROR(VLOOKUP(A8,MASTER_SKU!A:D,4,FALSE()),"") -> HIGH | C8: =SUMIF(RAW_Production_Orders!C:C,A8,RAW_Production_Orders!G:G)*IFERROR(VLOOKUP(A8,MASTER_SKU!A:H,8,FALSE()),0) -> 3040823.5 | D8: =SUMIF(RAW_Production_Orders!C:C,A8,RAW_Production_Orders!G:G)*IFERROR(VLOOKUP(A8,MASTER_SKU!A:I,9,FALSE()),0) -> 412531.3 | E8: =IF(C8=0,0,D8/C8) -> 0.13566434 | F8: =D8-IFERROR(VLOOKUP(A8,ANALYSIS_Scrap!A:K,11,FALSE()),0) -> -296734.94 | G8: =IF(C8=0,0,F8/C8) -> -0.097583743 | H8: =D8-F8 -> 709266.24 | I8: =IF(F8<0,"YES","") -> YES
A9: SKU-4421 | B9: =IFERROR(VLOOKUP(A9,MASTER_SKU!A:D,4,FALSE()),"") -> HIGH | C9: =SUMIF(RAW_Production_Orders!C:C,A9,RAW_Production_Orders!G:G)*IFERROR(VLOOKUP(A9,MASTER_SKU!A:H,8,FALSE()),0) -> 4901712 | D9: =SUMIF(RAW_Production_Orders!C:C,A9,RAW_Production_Orders!G:G)*IFERROR(VLOOKUP(A9,MASTER_SKU!A:I,9,FALSE()),0) -> 684798 | E9: =IF(C9=0,0,D9/C9) -> 0.13970588 | F9: =D9-IFERROR(VLOOKUP(A9,ANALYSIS_Scrap!A:K,11,FALSE()),0) -> -445702.8 | G9: =IF(C9=0,0,F9/C9) -> -0.090927986 | H9: =D9-F9 -> 1130500.8 | I9: =IF(F9<0,"YES","") -> YES
A10: SKU-4455 | B10: =IFERROR(VLOOKUP(A10,MASTER_SKU!A:D,4,FALSE()),"") -> HIGH | C10: =SUMIF(RAW_Production_Orders!C:C,A10,RAW_Production_Orders!G:G)*IFERROR(VLOOKUP(A10,MASTER_SKU!A:H,8,FALSE()),0) -> 4151329 | D10: =SUMIF(RAW_Production_Orders!C:C,A10,RAW_Production_Orders!G:G)*IFERROR(VLOOKUP(A10,MASTER_SKU!A:I,9,FALSE()),0) -> 580561.8 | E10: =IF(C10=0,0,D10/C10) -> 0.13984962 | F10: =D10-IFERROR(VLOOKUP(A10,ANALYSIS_Scrap!A:K,11,FALSE()),0) -> -307227.96 | G10: =IF(C10=0,0,F10/C10) -> -0.074007134 | H10: =D10-F10 -> 887789.76 | I10: =IF(F10<0,"YES","") -> YES
A11: SKU-4672 | B11: =IFERROR(VLOOKUP(A11,MASTER_SKU!A:D,4,FALSE()),"") -> HIGH | C11: =SUMIF(RAW_Production_Orders!C:C,A11,RAW_Production_Orders!G:G)*IFERROR(VLOOKUP(A11,MASTER_SKU!A:H,8,FALSE()),0) -> 1835096.2 | D11: =SUMIF(RAW_Production_Orders!C:C,A11,RAW_Production_Orders!G:G)*IFERROR(VLOOKUP(A11,MASTER_SKU!A:I,9,FALSE()),0) -> 251001 | E11: =IF(C11=0,0,D11/C11) -> 0.13677812 | F11: =D11-IFERROR(VLOOKUP(A11,ANALYSIS_Scrap!A:K,11,FALSE()),0) -> -120198.36 | G11: =IF(C11=0,0,F11/C11) -> -0.06549976 | H11: =D11-F11 -> 371199.36 | I11: =IF(F11<0,"YES","") -> YES
A12: SKU-5678 | B12: =IFERROR(VLOOKUP(A12,MASTER_SKU!A:D,4,FALSE()),"") -> HIGH | C12: =SUMIF(RAW_Production_Orders!C:C,A12,RAW_Production_Orders!G:G)*IFERROR(VLOOKUP(A12,MASTER_SKU!A:H,8,FALSE()),0) -> 500856 | D12: =SUMIF(RAW_Production_Orders!C:C,A12,RAW_Production_Orders!G:G)*IFERROR(VLOOKUP(A12,MASTER_SKU!A:I,9,FALSE()),0) -> 64134 | E12: =IF(C12=0,0,D12/C12) -> 0.12804878 | F12: =D12-IFERROR(VLOOKUP(A12,ANALYSIS_Scrap!A:K,11,FALSE()),0) -> -16346.4 | G12: =IF(C12=0,0,F12/C12) -> -0.032636926 | H12: =D12-F12 -> 80480.4 | I12: =IF(F12<0,"YES","") -> YES
A13: SKU-5244 | B13: =IFERROR(VLOOKUP(A13,MASTER_SKU!A:D,4,FALSE()),"") -> HIGH | C13: =SUMIF(RAW_Production_Orders!C:C,A13,RAW_Production_Orders!G:G)*IFERROR(VLOOKUP(A13,MASTER_SKU!A:H,8,FALSE()),0) -> 661360 | D13: =SUMIF(RAW_Production_Orders!C:C,A13,RAW_Production_Orders!G:G)*IFERROR(VLOOKUP(A13,MASTER_SKU!A:I,9,FALSE()),0) -> 84323.4 | E13: =IF(C13=0,0,D13/C13) -> 0.1275 | F13: =D13-IFERROR(VLOOKUP(A13,ANALYSIS_Scrap!A:K,11,FALSE()),0) -> -10492.92 | G13: =IF(C13=0,0,F13/C13) -> -0.015865671 | H13: =D13-F13 -> 94816.32 | I13: =IF(F13<0,"YES","") -> YES
A14: SKU-5455 | B14: =IFERROR(VLOOKUP(A14,MASTER_SKU!A:D,4,FALSE()),"") -> HIGH | C14: =SUMIF(RAW_Production_Orders!C:C,A14,RAW_Production_Orders!G:G)*IFERROR(VLOOKUP(A14,MASTER_SKU!A:H,8,FALSE()),0) -> 876806 | D14: =SUMIF(RAW_Production_Orders!C:C,A14,RAW_Production_Orders!G:G)*IFERROR(VLOOKUP(A14,MASTER_SKU!A:I,9,FALSE()),0) -> 112187.6 | E14: =IF(C14=0,0,D14/C14) -> 0.12795031 | F14: =D14-IFERROR(VLOOKUP(A14,ANALYSIS_Scrap!A:K,11,FALSE()),0) -> -10971.28 | G14: =IF(C14=0,0,F14/C14) -> -0.012512779 | H14: =D14-F14 -> 123158.88 | I14: =IF(F14<0,"YES","") -> YES
A15: SKU-5102 | B15: =IFERROR(VLOOKUP(A15,MASTER_SKU!A:D,4,FALSE()),"") -> MEDIUM | C15: =SUMIF(RAW_Production_Orders!C:C,A15,RAW_Production_Orders!G:G)*IFERROR(VLOOKUP(A15,MASTER_SKU!A:H,8,FALSE()),0) -> 1005977.5 | D15: =SUMIF(RAW_Production_Orders!C:C,A15,RAW_Production_Orders!G:G)*IFERROR(VLOOKUP(A15,MASTER_SKU!A:I,9,FALSE()),0) -> 131994.5 | E15: =IF(C15=0,0,D15/C15) -> 0.13121019 | F15: =D15-IFERROR(VLOOKUP(A15,ANALYSIS_Scrap!A:K,11,FALSE()),0) -> 8416.1 | G15: =IF(C15=0,0,F15/C15) -> 0.0083660917 | H15: =D15-F15 -> 123578.4 | I15: =IF(F15<0,"YES","")
A16: SKU-5108 | B16: =IFERROR(VLOOKUP(A16,MASTER_SKU!A:D,4,FALSE()),"") -> MEDIUM | C16: =SUMIF(RAW_Production_Orders!C:C,A16,RAW_Production_Orders!G:G)*IFERROR(VLOOKUP(A16,MASTER_SKU!A:H,8,FALSE()),0) -> 1012800.4 | D16: =SUMIF(RAW_Production_Orders!C:C,A16,RAW_Production_Orders!G:G)*IFERROR(VLOOKUP(A16,MASTER_SKU!A:I,9,FALSE()),0) -> 134085.4 | E16: =IF(C16=0,0,D16/C16) -> 0.13239075 | F16: =D16-IFERROR(VLOOKUP(A16,ANALYSIS_Scrap!A:K,11,FALSE()),0) -> 11775.4 | G16: =IF(C16=0,0,F16/C16) -> 0.011626575 | H16: =D16-F16 -> 122310 | I16: =IF(F16<0,"YES","")
A17: SKU-5512 | B17: =IFERROR(VLOOKUP(A17,MASTER_SKU!A:D,4,FALSE()),"") -> MEDIUM | C17: =SUMIF(RAW_Production_Orders!C:C,A17,RAW_Production_Orders!G:G)*IFERROR(VLOOKUP(A17,MASTER_SKU!A:H,8,FALSE()),0) -> 735451.2 | D17: =SUMIF(RAW_Production_Orders!C:C,A17,RAW_Production_Orders!G:G)*IFERROR(VLOOKUP(A17,MASTER_SKU!A:I,9,FALSE()),0) -> 96574.4 | E17: =IF(C17=0,0,D17/C17) -> 0.13131313 | F17: =D17-IFERROR(VLOOKUP(A17,ANALYSIS_Scrap!A:K,11,FALSE()),0) -> 10216.64 | G17: =IF(C17=0,0,F17/C17) -> 0.013891663 | H17: =D17-F17 -> 86357.76 | I17: =IF(F17<0,"YES","")
... A29: SKU-1001 | B29: =IFERROR(VLOOKUP(A29,MASTER_SKU!A:D,4,FALSE()),"") -> LOW | C29: =SUMIF(RAW_Production_Orders!C:C,A29,RAW_Production_Orders!G:G)*IFERROR(VLOOKUP(A29,MASTER_SKU!A:H,8,FALSE()),0) -> 8654373 | D29: =SUMIF(RAW_Production_Orders!C:C,A29,RAW_Production_Orders!G:G)*IFERROR(VLOOKUP(A29,MASTER_SKU!A:I,9,FALSE()),0) -> 1967575.4 | E29: =IF(C29=0,0,D29/C29) -> 0.22735043 | F29: =D29-IFERROR(VLOOKUP(A29,ANALYSIS_Scrap!A:K,11,FALSE()),0) -> 1513261.2 | G29: =IF(C29=0,0,F29/C29) -> 0.17485509 | H29: =D29-F29 -> 454314.24 | I29: =IF(F29<0,"YES","")
A30: TOTAL | C30: =SUM(C6:C29) -> 72204639 | D30: =SUM(D6:D29) -> 14090299 | E30: =IF(C30=0,0,D30/C30) -> 0.19514395 | F30: =SUM(F6:F29) -> 6200855.2 | G30: =IF(C30=0,0,F30/C30) -> 0.085878902 | H30: =SUM(H6:H29) -> 7889443.4
A32: Phantom SKU Count (negative True CM): | B32: =COUNTIF(I6:I29,"YES") -> 9
A34: SKU RATIONALIZATION ASSUMPTIONS
A35: Phantom SKU Margin Recovery Rate: | B35: 0.093
A37: Total Margin Gap (Phantom SKUs): | B37: =SUMIF(F6:F29,"<0",H6:H29) -> 4478755.4
A38: SKU Rationalization Opportunity: | B38: =B37*B35 -> 416524.26
